terraform_python/__init__.py
terraform_python/terraform.py
terraform_python/classes/__init__.py
terraform_python/classes/base.py
terraform_python/classes/defaults.py
terraform_python/classes/exceptions.py
terraform_python/classes/state.py
terraform_python/classes/workspace.py
terraform_python/utils/__init__.py
terraform_python/utils/colors.py
terraform_python/utils/logger.py
terraform_python/utils/utils.py
terraform_python-0.0.1.dist-info/METADATA
terraform_python-0.0.1.dist-info/WHEEL
terraform_python-0.0.1.dist-info/licenses/LICENSE
terraform_python-0.0.1.dist-info/RECORD
